{"version":"4.1.0","colorNotes":[{"b":8,"r":0,"i":0},{"b":8,"r":0,"i":1},{"b":8.5,"r":0,"i":2},{"b":9,"r":0,"i":3},{"b":9.5,"r":0,"i":4},{"b":11,"r":0,"i":5},{"b":11,"r":0,"i":6},{"b":12,"r":0,"i":7},{"b":12,"r":0,"i":8},{"b":12.5,"r":0,"i":4},{"b":13,"r":0,"i":9},{"b":13.5,"r":0,"i":10},{"b":15,"r":0,"i":11},{"b":15,"r":0,"i":12},{"b":16,"r":0,"i":13},{"b":16.5,"r":0,"i":14},{"b":17,"r":0,"i":12},{"b":17.5,"r":0,"i":15},{"b":19,"r":0,"i":16},{"b":19,"r":0,"i":17},{"b":20,"r":0,"i":18},{"b":20.5,"r":0,"i":3},{"b":21,"r":0,"i":5},{"b":21.5,"r":0,"i":6},{"b":23,"r":0,"i":11},{"b":23,"r":0,"i":7},{"b":24,"r":0,"i":19},{"b":24,"r":0,"i":10},{"b":24.5,"r":0,"i":9},{"b":25,"r":0,"i":4},{"b":25.5,"r":0,"i":20},{"b":26,"r":0,"i":21},{"b":26.25,"r":0,"i":1},{"b":26.5,"r":0,"i":0},{"b":26.75,"r":0,"i":22},{"b":27,"r":0,"i":5},{"b":28,"r":0,"i":11},{"b":28.5,"r":0,"i":6},{"b":29,"r":0,"i":23},{"b":29.25,"r":0,"i":24},{"b":29.5,"r":0,"i":25},{"b":29.75,"r":0,"i":26},{"b":30,"r":0,"i":27},{"b":30.75,"r":0,"i":18},{"b":31.5,"r":0,"i":10},{"b":32,"r":0,"i":0},{"b":32,"r":0,"i":28},{"b":32.5,"r":0,"i":3},{"b":33,"r":0,"i":5},{"b":33.5,"r":0,"i":6},{"b":34,"r":0,"i":0},{"b":34.25,"r":0,"i":7},{"b":34.5,"r":0,"i":2},{"b":34.75,"r":0,"i":26},{"b":35,"r":0,"i":18},{"b":36,"r":0,"i":24},{"b":36,"r":0,"i":20},{"b":36.5,"r":0,"i":10},{"b":37,"r":0,"i":17},{"b":37.25,"r":0,"i":25},{"b":37.5,"r":0,"i":29},{"b":37.75,"r":0,"i":2},{"b":38,"r":0,"i":30},{"b":38.25,"r":0,"i":18},{"b":38.75,"r":0,"i":7},{"b":39.25,"r":0,"i":26},{"b":39.5,"r":0,"i":19},{"b":40,"r":0,"i":24},{"b":40,"r":0,"i":20},{"b":40.5,"r":0,"i":4},{"b":41,"r":0,"i":9},{"b":41.5,"r":0,"i":31},{"b":42,"r":0,"i":3},{"b":42.75,"r":0,"i":6},{"b":43.5,"r":0,"i":28},{"b":44,"r":0,"i":7},{"b":44,"r":0,"i":8},{"b":44.75,"r":0,"i":26},{"b":45.5,"r":0,"i":10},{"b":46,"r":0,"i":20},{"b":46.75,"r":0,"i":4},{"b":47.5,"r":0,"i":21},{"b":47.5,"r":0,"i":17},{"b":48,"r":0,"i":0},{"b":48,"r":0,"i":28},{"b":48.5,"r":0,"i":3},{"b":49,"r":0,"i":5},{"b":49.5,"r":0,"i":6},{"b":50,"r":0,"i":28},{"b":50.75,"r":0,"i":10},{"b":51.5,"r":0,"i":8},{"b":52,"r":0,"i":4},{"b":52.75,"r":0,"i":6},{"b":53.5,"r":0,"i":31},{"b":54,"r":0,"i":8},{"b":54.75,"r":0,"i":6},{"b":55.5,"r":0,"i":32},{"b":55.5,"r":0,"i":8},{"b":56,"r":0,"i":31},{"b":56,"r":0,"i":21},{"b":56.5,"r":0,"i":6},{"b":57,"r":0,"i":0},{"b":57.5,"r":0,"i":3},{"b":58,"r":0,"i":10},{"b":58.75,"r":0,"i":17},{"b":59.5,"r":0,"i":4},{"b":60,"r":0,"i":29},{"b":60.75,"r":0,"i":30},{"b":61.5,"r":0,"i":2},{"b":62,"r":0,"i":33},{"b":62.75,"r":0,"i":25},{"b":63.5,"r":0,"i":9},{"b":64,"r":0,"i":19},{"b":64,"r":0,"i":10},{"b":64.5,"r":0,"i":24},{"b":65,"r":0,"i":4},{"b":65.5,"r":0,"i":17},{"b":66,"r":0,"i":21},{"b":66.75,"r":0,"i":3},{"b":67.5,"r":0,"i":28},{"b":68,"r":0,"i":5},{"b":68,"r":0,"i":6},{"b":70,"r":0,"i":11},{"b":70,"r":0,"i":7},{"b":72,"r":0,"i":26},{"b":72.75,"r":0,"i":10},{"b":73.5,"r":0,"i":20},{"b":74.25,"r":0,"i":4},{"b":75,"r":0,"i":21},{"b":75.75,"r":0,"i":30},{"b":75.75,"r":0,"i":4},{"b":76.5,"r":0,"i":34},{"b":76.5,"r":0,"i":35},{"b":77.5,"r":0,"i":6},{"b":77.75,"r":0,"i":4},{"b":78,"r":0,"i":8},{"b":78.75,"r":0,"i":26},{"b":79.5,"r":0,"i":20},{"b":80,"r":0,"i":16},{"b":80.75,"r":0,"i":6},{"b":81.5,"r":0,"i":28},{"b":82,"r":0,"i":33},{"b":83,"r":0,"i":36},{"b":83.75,"r":0,"i":37},{"b":84.5,"r":0,"i":38},{"b":85.5,"r":0,"i":39},{"b":85.75,"r":0,"i":40},{"b":86,"r":0,"i":41},{"b":86.75,"r":0,"i":31},{"b":87.5,"r":0,"i":32},{"b":88,"r":0,"i":31},{"b":88,"r":0,"i":17},{"b":89,"r":0,"i":18},{"b":89,"r":0,"i":3},{"b":91.5,"r":0,"i":30},{"b":91.5,"r":0,"i":34},{"b":92.5,"r":0,"i":4},{"b":92.5,"r":0,"i":35},{"b":93.5,"r":0,"i":30},{"b":93.5,"r":0,"i":34},{"b":95,"r":0,"i":11},{"b":95.5,"r":0,"i":7},{"b":96.5,"r":0,"i":10},{"b":96.5,"r":0,"i":26},{"b":99.5,"r":0,"i":4},{"b":100,"r":0,"i":20},{"b":101,"r":0,"i":31},{"b":102.5,"r":0,"i":13},{"b":102.5,"r":0,"i":18},{"b":104,"r":0,"i":24},{"b":104.75,"r":0,"i":10},{"b":105.5,"r":0,"i":4},{"b":106,"r":0,"i":17},{"b":107,"r":0,"i":31},{"b":107.75,"r":0,"i":32},{"b":107.75,"r":0,"i":40},{"b":108.5,"r":0,"i":42},{"b":108.5,"r":0,"i":43},{"b":109.5,"r":0,"i":28},{"b":109.75,"r":0,"i":44},{"b":110,"r":0,"i":5},{"b":110.75,"r":0,"i":13},{"b":111.5,"r":0,"i":45},{"b":112,"r":0,"i":4},{"b":112.75,"r":0,"i":17},{"b":113.5,"r":0,"i":21},{"b":114,"r":0,"i":3},{"b":115,"r":0,"i":6},{"b":115.75,"r":0,"i":11},{"b":115.75,"r":0,"i":7},{"b":116.5,"r":0,"i":21},{"b":116.5,"r":0,"i":17},{"b":117.5,"r":0,"i":4},{"b":117.75,"r":0,"i":29},{"b":118,"r":0,"i":2},{"b":118.75,"r":0,"i":0},{"b":119.5,"r":0,"i":5},{"b":120,"r":0,"i":11},{"b":120,"r":0,"i":6},{"b":121,"r":0,"i":10},{"b":121,"r":0,"i":8},{"b":123.5,"r":0,"i":17},{"b":124.5,"r":0,"i":4},{"b":125.5,"r":0,"i":31},{"b":125.5,"r":0,"i":3},{"b":127,"r":0,"i":6},{"b":127.5,"r":0,"i":28},{"b":128.5,"r":0,"i":5},{"b":128.5,"r":0,"i":3},{"b":131.5,"r":0,"i":6},{"b":132,"r":0,"i":28},{"b":133,"r":0,"i":3},{"b":134.5,"r":0,"i":17},{"b":134.75,"r":0,"i":16},{"b":135,"r":0,"i":46},{"b":135.25,"r":0,"i":4},{"b":135.5,"r":0,"i":17},{"b":135.75,"r":0,"i":21},{"b":136,"r":0,"i":22},{"b":136,"r":0,"i":3},{"b":136.5,"r":0,"i":6},{"b":137,"r":0,"i":11},{"b":137,"r":0,"i":33},{"b":137.5,"r":0,"i":10},{"b":137.75,"r":0,"i":9},{"b":138,"r":0,"i":4},{"b":138.25,"r":0,"i":24},{"b":138.5,"r":0,"i":21},{"b":139,"r":0,"i":0},{"b":139,"r":0,"i":1},{"b":139.5,"r":0,"i":3},{"b":140,"r":0,"i":5},{"b":140,"r":0,"i":6},{"b":140.5,"r":0,"i":3},{"b":141,"r":0,"i":4},{"b":141,"r":0,"i":17},{"b":141.5,"r":0,"i":16},{"b":141.75,"r":0,"i":29},{"b":142,"r":0,"i":28},{"b":142.5,"r":0,"i":5},{"b":143,"r":0,"i":28},{"b":143.25,"r":0,"i":6},{"b":143.5,"r":0,"i":23},{"b":144,"r":0,"i":12},{"b":144,"r":0,"i":15},{"b":146,"r":0,"i":4},{"b":146.25,"r":0,"i":6},{"b":146.5,"r":0,"i":31},{"b":147,"r":0,"i":0},{"b":147,"r":0,"i":44},{"b":147.5,"r":0,"i":2},{"b":147.75,"r":0,"i":30},{"b":148,"r":0,"i":18},{"b":148.5,"r":0,"i":10},{"b":149,"r":0,"i":4},{"b":149,"r":0,"i":47},{"b":149.5,"r":0,"i":16},{"b":149.75,"r":0,"i":6},{"b":150,"r":0,"i":28},{"b":150.5,"r":0,"i":5},{"b":151,"r":0,"i":11},{"b":151,"r":0,"i":33},{"b":151.5,"r":0,"i":14},{"b":151.75,"r":0,"i":1},{"b":152,"r":0,"i":15},{"b":152.25,"r":0,"i":3},{"b":152.5,"r":0,"i":10},{"b":152.75,"r":0,"i":13},{"b":153,"r":0,"i":11},{"b":153,"r":0,"i":48},{"b":153.5,"r":0,"i":7},{"b":153.75,"r":0,"i":10},{"b":154,"r":0,"i":26},{"b":154.5,"r":0,"i":24},{"b":154.75,"r":0,"i":4},{"b":155,"r":0,"i":26},{"b":155,"r":0,"i":9},{"b":155.5,"r":0,"i":16},{"b":155.75,"r":0,"i":29},{"b":156,"r":0,"i":28},{"b":156.5,"r":0,"i":5},{"b":157,"r":0,"i":11},{"b":157,"r":0,"i":6},{"b":157.5,"r":0,"i":3},{"b":158,"r":0,"i":17},{"b":158.5,"r":0,"i":3},{"b":158.75,"r":0,"i":10},{"b":159,"r":0,"i":30},{"b":159,"r":0,"i":49},{"b":159.5,"r":0,"i":8},{"b":159.75,"r":0,"i":4},{"b":160,"r":0,"i":26},{"b":160.5,"r":0,"i":3},{"b":160.75,"r":0,"i":31},{"b":161,"r":0,"i":30},{"b":161,"r":0,"i":49},{"b":161.5,"r":0,"i":35},{"b":162,"r":0,"i":17},{"b":162.5,"r":0,"i":3},{"b":162.75,"r":0,"i":18},{"b":163,"r":0,"i":13},{"b":163,"r":0,"i":50},{"b":163.5,"r":0,"i":45},{"b":164,"r":0,"i":51},{"b":164.5,"r":0,"i":10},{"b":164.75,"r":0,"i":20},{"b":165,"r":0,"i":4},{"b":165.5,"r":0,"i":31},{"b":166,"r":0,"i":0},{"b":166.5,"r":0,"i":5},{"b":166.75,"r":0,"i":6},{"b":167,"r":0,"i":28},{"b":167.25,"r":0,"i":7},{"b":167.5,"r":0,"i":2},{"b":167.75,"r":0,"i":26},{"b":168,"r":0,"i":18},{"b":168.5,"r":0,"i":10},{"b":169,"r":0,"i":52},{"b":169,"r":0,"i":15},{"b":169.5,"r":0,"i":31},{"b":169.75,"r":0,"i":12},{"b":170,"r":0,"i":0},{"b":170.25,"r":0,"i":6},{"b":170.5,"r":0,"i":5},{"b":171,"r":0,"i":11},{"b":171,"r":0,"i":7},{"b":171.5,"r":0,"i":10},{"b":172,"r":0,"i":1},{"b":172,"r":0,"i":15},{"b":172.5,"r":0,"i":16},{"b":173,"r":0,"i":18},{"b":173,"r":0,"i":3},{"b":173.5,"r":0,"i":6},{"b":173.75,"r":0,"i":2},{"b":174,"r":0,"i":7},{"b":174.25,"r":0,"i":18},{"b":174.5,"r":0,"i":26},{"b":175,"r":0,"i":10},{"b":175,"r":0,"i":20},{"b":175.5,"r":0,"i":15},{"b":176,"r":0,"i":16},{"b":176,"r":0,"i":9},{"b":176.5,"r":0,"i":3},{"b":177,"r":0,"i":11},{"b":177,"r":0,"i":6},{"b":177.5,"r":0,"i":14},{"b":177.75,"r":0,"i":12},{"b":178,"r":0,"i":15},{"b":178.25,"r":0,"i":1},{"b":178.5,"r":0,"i":14},{"b":179,"r":0,"i":11},{"b":179,"r":0,"i":29},{"b":179.5,"r":0,"i":30},{"b":180,"r":0,"i":2},{"b":180,"r":0,"i":33},{"b":180.5,"r":0,"i":18},{"b":181,"r":0,"i":10},{"b":181,"r":0,"i":1},{"b":181.5,"r":0,"i":24},{"b":181.75,"r":0,"i":4},{"b":182,"r":0,"i":6},{"b":182.25,"r":0,"i":31},{"b":182.5,"r":0,"i":7},{"b":183,"r":0,"i":18},{"b":183,"r":0,"i":26},{"b":183.5,"r":0,"i":24},{"b":183.75,"r":0,"i":10},{"b":184,"r":0,"i":26},{"b":184.5,"r":0,"i":20},{"b":185,"r":0,"i":4},{"b":185,"r":0,"i":17},{"b":185.5,"r":0,"i":21},{"b":185.75,"r":0,"i":22},{"b":186,"r":0,"i":0},{"b":186.25,"r":0,"i":6},{"b":186.5,"r":0,"i":5},{"b":187,"r":0,"i":28},{"b":187,"r":0,"i":3},{"b":187.5,"r":0,"i":10},{"b":188,"r":0,"i":4},{"b":188,"r":0,"i":17},{"b":188.5,"r":0,"i":16},{"b":189,"r":0,"i":12},{"b":189,"r":0,"i":15},{"b":189.5,"r":0,"i":16},{"b":189.75,"r":0,"i":6},{"b":190,"r":0,"i":28},{"b":190.5,"r":0,"i":5},{"b":191,"r":0,"i":11},{"b":191,"r":0,"i":33},{"b":191.5,"r":0,"i":10},{"b":192,"r":0,"i":18},{"b":192,"r":0,"i":9},{"b":192.5,"r":0,"i":10},{"b":193,"r":0,"i":4},{"b":193,"r":0,"i":20},{"b":193.5,"r":0,"i":21},{"b":194,"r":0,"i":0},{"b":194.25,"r":0,"i":6},{"b":194.5,"r":0,"i":2},{"b":195,"r":0,"i":0},{"b":195,"r":0,"i":3},{"b":195.5,"r":0,"i":10},{"b":196,"r":0,"i":4},{"b":196,"r":0,"i":17},{"b":196.5,"r":0,"i":31},{"b":197,"r":0,"i":53},{"b":197,"r":0,"i":41},{"b":197.5,"r":0,"i":31},{"b":198,"r":0,"i":3},{"b":198.25,"r":0,"i":28},{"b":198.5,"r":0,"i":6},{"b":198.75,"r":0,"i":2},{"b":199,"r":0,"i":7},{"b":199.25,"r":0,"i":18},{"b":199.5,"r":0,"i":26},{"b":199.75,"r":0,"i":14},{"b":200,"r":0,"i":24},{"b":200.5,"r":0,"i":26},{"b":201,"r":0,"i":4},{"b":201,"r":0,"i":20},{"b":201.5,"r":0,"i":21},{"b":201.75,"r":0,"i":1},{"b":202,"r":0,"i":0},{"b":202.25,"r":0,"i":12},{"b":202.5,"r":0,"i":5},{"b":203,"r":0,"i":11},{"b":203,"r":0,"i":6},{"b":203.5,"r":0,"i":8},{"b":204,"r":0,"i":10},{"b":204,"r":0,"i":26},{"b":204.5,"r":0,"i":20},{"b":205,"r":0,"i":4},{"b":205,"r":0,"i":17},{"b":205.5,"r":0,"i":21},{"b":205.75,"r":0,"i":12},{"b":206,"r":0,"i":0},{"b":206.25,"r":0,"i":6},{"b":206.5,"r":0,"i":2},{"b":206.75,"r":0,"i":7},{"b":207.5,"r":0,"i":54},{"b":208,"r":0,"i":11},{"b":208,"r":0,"i":8},{"b":208.5,"r":0,"i":10},{"b":209,"r":0,"i":18},{"b":209,"r":0,"i":26},{"b":209.5,"r":0,"i":14},{"b":209.75,"r":0,"i":24},{"b":210,"r":0,"i":4},{"b":210.25,"r":0,"i":6},{"b":210.5,"r":0,"i":31},{"b":211,"r":0,"i":0},{"b":211,"r":0,"i":12},{"b":211.5,"r":0,"i":6},{"b":212,"r":0,"i":5},{"b":212,"r":0,"i":3},{"b":212.5,"r":0,"i":18},{"b":213,"r":0,"i":10},{"b":213,"r":0,"i":9},{"b":213.5,"r":0,"i":4},{"b":213.75,"r":0,"i":24},{"b":214,"r":0,"i":21},{"b":214.25,"r":0,"i":1},{"b":214.5,"r":0,"i":0},{"b":214.75,"r":0,"i":3},{"b":215.5,"r":0,"i":6},{"b":215.75,"r":0,"i":2},{"b":216,"r":0,"i":7},{"b":216,"r":0,"i":8},{"b":216.5,"r":0,"i":26},{"b":217,"r":0,"i":4},{"b":217,"r":0,"i":20},{"b":217.5,"r":0,"i":31},{"b":218,"r":0,"i":41},{"b":218.5,"r":0,"i":31},{"b":219,"r":0,"i":32},{"b":219,"r":0,"i":17},{"b":219.5,"r":0,"i":31},{"b":220,"r":0,"i":0},{"b":220,"r":0,"i":3},{"b":220.5,"r":0,"i":6},{"b":221,"r":0,"i":2},{"b":221,"r":0,"i":7},{"b":221.5,"r":0,"i":18},{"b":221.75,"r":0,"i":26},{"b":222,"r":0,"i":10},{"b":222.25,"r":0,"i":24},{"b":222.5,"r":0,"i":4},{"b":223,"r":0,"i":21},{"b":223,"r":0,"i":17},{"b":223.5,"r":0,"i":0},{"b":224,"r":0,"i":5},{"b":224,"r":0,"i":3},{"b":224.5,"r":0,"i":6},{"b":225,"r":0,"i":32},{"b":225,"r":0,"i":8},{"b":225.5,"r":0,"i":21},{"b":225.75,"r":0,"i":54},{"b":226,"r":0,"i":0},{"b":226.25,"r":0,"i":7},{"b":226.5,"r":0,"i":5},{"b":227,"r":0,"i":0},{"b":227,"r":0,"i":28},{"b":227.5,"r":0,"i":10},{"b":228,"r":0,"i":4},{"b":228,"r":0,"i":17},{"b":228.5,"r":0,"i":16},{"b":229,"r":0,"i":55},{"b":229,"r":0,"i":15},{"b":229.5,"r":0,"i":16},{"b":229.75,"r":0,"i":17},{"b":230,"r":0,"i":18},{"b":230.25,"r":0,"i":3},{"b":230.5,"r":0,"i":2},{"b":230.75,"r":0,"i":6},{"b":231,"r":0,"i":0},{"b":231.25,"r":0,"i":7},{"b":231.5,"r":0,"i":19},{"b":231.75,"r":0,"i":26},{"b":232,"r":0,"i":4},{"b":232.75,"r":0,"i":3},{"b":233.5,"r":0,"i":6},{"b":234,"r":0,"i":2},{"b":234,"r":0,"i":5},{"b":235,"r":0,"i":8},{"b":235.75,"r":0,"i":48},{"b":235.75,"r":0,"i":54},{"b":236.5,"r":0,"i":56},{"b":236.5,"r":0,"i":57},{"b":237.25,"r":0,"i":9},{"b":237.667,"r":0,"i":25},{"b":238,"r":0,"i":20},{"b":238.75,"r":0,"i":27},{"b":239.5,"r":0,"i":15},{"b":240,"r":0,"i":16},{"b":240,"r":0,"i":17},{"b":240.75,"r":0,"i":4},{"b":241.5,"r":0,"i":3},{"b":242,"r":0,"i":31},{"b":242,"r":0,"i":21},{"b":243,"r":0,"i":6},{"b":243.75,"r":0,"i":11},{"b":243.75,"r":0,"i":7},{"b":244.5,"r":0,"i":21},{"b":244.5,"r":0,"i":17},{"b":245.5,"r":0,"i":4},{"b":245.75,"r":0,"i":29},{"b":246,"r":0,"i":2},{"b":246.75,"r":0,"i":0},{"b":247.5,"r":0,"i":5},{"b":248,"r":0,"i":11},{"b":248,"r":0,"i":6},{"b":249,"r":0,"i":10},{"b":249,"r":0,"i":8},{"b":251.5,"r":0,"i":17},{"b":252.5,"r":0,"i":4},{"b":253.5,"r":0,"i":31},{"b":253.5,"r":0,"i":3},{"b":255,"r":0,"i":6},{"b":255.5,"r":0,"i":28},{"b":256.5,"r":0,"i":5},{"b":256.5,"r":0,"i":3},{"b":258,"r":0,"i":11},{"b":258,"r":0,"i":6},{"b":259.5,"r":0,"i":8},{"b":260,"r":0,"i":10},{"b":261,"r":0,"i":9},{"b":262.5,"r":0,"i":0},{"b":262.75,"r":0,"i":12},{"b":263,"r":0,"i":2},{"b":263.25,"r":0,"i":6},{"b":263.5,"r":0,"i":0},{"b":263.75,"r":0,"i":7},{"b":264,"r":0,"i":19},{"b":264,"r":0,"i":10},{"b":264.5,"r":0,"i":4},{"b":265,"r":0,"i":16},{"b":265,"r":0,"i":17},{"b":265.5,"r":0,"i":3},{"b":265.75,"r":0,"i":28},{"b":266,"r":0,"i":6},{"b":266.25,"r":0,"i":2},{"b":266.5,"r":0,"i":7},{"b":267,"r":0,"i":18},{"b":267,"r":0,"i":26},{"b":267.5,"r":0,"i":10},{"b":268,"r":0,"i":4},{"b":268,"r":0,"i":20},{"b":268.5,"r":0,"i":10},{"b":269,"r":0,"i":11},{"b":269,"r":0,"i":6},{"b":269.5,"r":0,"i":8},{"b":269.75,"r":0,"i":14},{"b":270,"r":0,"i":26},{"b":270.25,"r":0,"i":4},{"b":270.5,"r":0,"i":20},{"b":271,"r":0,"i":21},{"b":271,"r":0,"i":9},{"b":271.5,"r":0,"i":0},{"b":271.75,"r":0,"i":22},{"b":272,"r":0,"i":2},{"b":272.5,"r":0,"i":6},{"b":273,"r":0,"i":11},{"b":273,"r":0,"i":33},{"b":273.5,"r":0,"i":14},{"b":273.75,"r":0,"i":1},{"b":274,"r":0,"i":15},{"b":274.25,"r":0,"i":3},{"b":274.5,"r":0,"i":10},{"b":275,"r":0,"i":11},{"b":275,"r":0,"i":6},{"b":275.5,"r":0,"i":8},{"b":276,"r":0,"i":10},{"b":276,"r":0,"i":26},{"b":276.5,"r":0,"i":20},{"b":277,"r":0,"i":4},{"b":277,"r":0,"i":17},{"b":277.5,"r":0,"i":21},{"b":277.75,"r":0,"i":3},{"b":278,"r":0,"i":0},{"b":278.25,"r":0,"i":6},{"b":278.5,"r":0,"i":2},{"b":279,"r":0,"i":7},{"b":279,"r":0,"i":8},{"b":279.25,"r":0,"i":18},{"b":279.5,"r":0,"i":26},{"b":279.75,"r":0,"i":10},{"b":280,"r":0,"i":24},{"b":280,"r":0,"i":20},{"b":280.5,"r":0,"i":4},{"b":281,"r":0,"i":58},{"b":281,"r":0,"i":59},{"b":281.5,"r":0,"i":41},{"b":281.75,"r":0,"i":17},{"b":282,"r":0,"i":21},{"b":282.25,"r":0,"i":3},{"b":282.5,"r":0,"i":0},{"b":283,"r":0,"i":5},{"b":283,"r":0,"i":6},{"b":283.5,"r":0,"i":28},{"b":284,"r":0,"i":5},{"b":284,"r":0,"i":3},{"b":284.5,"r":0,"i":6},{"b":285,"r":0,"i":7},{"b":285,"r":0,"i":8},{"b":285.5,"r":0,"i":60},{"b":285.75,"r":0,"i":11},{"b":286,"r":0,"i":7},{"b":286.25,"r":0,"i":10},{"b":286.5,"r":0,"i":26},{"b":287,"r":0,"i":4},{"b":287,"r":0,"i":20},{"b":287.5,"r":0,"i":21},{"b":288,"r":0,"i":0},{"b":288,"r":0,"i":1},{"b":288.5,"r":0,"i":3},{"b":289,"r":0,"i":5},{"b":289,"r":0,"i":6},{"b":289.5,"r":0,"i":7},{"b":289.75,"r":0,"i":18},{"b":290,"r":0,"i":26},{"b":290.25,"r":0,"i":19},{"b":290.5,"r":0,"i":20},{"b":291,"r":0,"i":4},{"b":291,"r":0,"i":17},{"b":291.5,"r":0,"i":31},{"b":292,"r":0,"i":0},{"b":292,"r":0,"i":12},{"b":292.5,"r":0,"i":5},{"b":293,"r":0,"i":11},{"b":293,"r":0,"i":6},{"b":293.5,"r":0,"i":8},{"b":293.75,"r":0,"i":10},{"b":294,"r":0,"i":26},{"b":294.25,"r":0,"i":4},{"b":294.5,"r":0,"i":24},{"b":294.75,"r":0,"i":21},{"b":295,"r":0,"i":1},{"b":295.25,"r":0,"i":0},{"b":295.5,"r":0,"i":12},{"b":295.75,"r":0,"i":2},{"b":296,"r":0,"i":6},{"b":296.5,"r":0,"i":8},{"b":297,"r":0,"i":18},{"b":297,"r":0,"i":26},{"b":297.5,"r":0,"i":24},{"b":297.75,"r":0,"i":19},{"b":298,"r":0,"i":26},{"b":300,"r":0,"i":0},{"b":300,"r":0,"i":3},{"b":301.5,"r":0,"i":13},{"b":302,"r":0,"i":14},{"b":302.5,"r":0,"i":12},{"b":303,"r":0,"i":15},{"b":303.5,"r":0,"i":16},{"b":303.5,"r":0,"i":17},{"b":304.5,"r":0,"i":18},{"b":304.5,"r":0,"i":3},{"b":305,"r":0,"i":2},{"b":305,"r":0,"i":6},{"b":306,"r":0,"i":11},{"b":306,"r":0,"i":33},{"b":308,"r":0,"i":21},{"b":308,"r":0,"i":17},{"b":309.5,"r":0,"i":15},{"b":310,"r":0,"i":12},{"b":310.5,"r":0,"i":14},{"b":311.5,"r":0,"i":11},{"b":311.5,"r":0,"i":6},{"b":312,"r":0,"i":10},{"b":312,"r":0,"i":8},{"b":312.5,"r":0,"i":4},{"b":313,"r":0,"i":21},{"b":313,"r":0,"i":26},{"b":313.5,"r":0,"i":12},{"b":313.75,"r":0,"i":0},{"b":314,"r":0,"i":6},{"b":316,"r":0,"i":10},{"b":316,"r":0,"i":20},{"b":317.5,"r":0,"i":4},{"b":318,"r":0,"i":17},{"b":318.5,"r":0,"i":21},{"b":319,"r":0,"i":12},{"b":319.5,"r":0,"i":28},{"b":319.5,"r":0,"i":6},{"b":320.5,"r":0,"i":5},{"b":320.5,"r":0,"i":3},{"b":321,"r":0,"i":32},{"b":321,"r":0,"i":17},{"b":321.5,"r":0,"i":16},{"b":322,"r":0,"i":55},{"b":322,"r":0,"i":15},{"b":324,"r":0,"i":10},{"b":324,"r":0,"i":1},{"b":325.5,"r":0,"i":11},{"b":326,"r":0,"i":29},{"b":326.5,"r":0,"i":23},{"b":327.5,"r":0,"i":4},{"b":327.5,"r":0,"i":17},{"b":328,"r":0,"i":31},{"b":328,"r":0,"i":21},{"b":328.5,"r":0,"i":3},{"b":329,"r":0,"i":28},{"b":329.5,"r":0,"i":6},{"b":331,"r":0,"i":5},{"b":331,"r":0,"i":3},{"b":332,"r":0,"i":11},{"b":332,"r":0,"i":6},{"b":332.5,"r":0,"i":8},{"b":333,"r":0,"i":10},{"b":333.5,"r":0,"i":26},{"b":335,"r":0,"i":4},{"b":335,"r":0,"i":20},{"b":336,"r":0,"i":26},{"b":336,"r":0,"i":9},{"b":336.5,"r":0,"i":10},{"b":337,"r":0,"i":20},{"b":337.5,"r":0,"i":28},{"b":338,"r":0,"i":6},{"b":338.75,"r":0,"i":3},{"b":339.5,"r":0,"i":10},{"b":340,"r":0,"i":9},{"b":340.75,"r":0,"i":4},{"b":341.5,"r":0,"i":24},{"b":342,"r":0,"i":31},{"b":342.75,"r":0,"i":4},{"b":343.5,"r":0,"i":31},{"b":343.5,"r":0,"i":54},{"b":344,"r":0,"i":7},{"b":344,"r":0,"i":8},{"b":344.5,"r":0,"i":26},{"b":345,"r":0,"i":4},{"b":345,"r":0,"i":20},{"b":345.5,"r":0,"i":16},{"b":345.75,"r":0,"i":6},{"b":346,"r":0,"i":0},{"b":346.25,"r":0,"i":7},{"b":346.5,"r":0,"i":2},{"b":347,"r":0,"i":18},{"b":347,"r":0,"i":26},{"b":347.5,"r":0,"i":20},{"b":348,"r":0,"i":14},{"b":348,"r":0,"i":17},{"b":348.5,"r":0,"i":4},{"b":349,"r":0,"i":21},{"b":349,"r":0,"i":24},{"b":349.5,"r":0,"i":1},{"b":349.75,"r":0,"i":0},{"b":350,"r":0,"i":12},{"b":350.25,"r":0,"i":2},{"b":350.5,"r":0,"i":6},{"b":351,"r":0,"i":0},{"b":351,"r":0,"i":7},{"b":351.5,"r":0,"i":26},{"b":351.75,"r":0,"i":19},{"b":352,"r":0,"i":24},{"b":352,"r":0,"i":20},{"b":352.5,"r":0,"i":26},{"b":353,"r":0,"i":4},{"b":353,"r":0,"i":20},{"b":353.5,"r":0,"i":16},{"b":354,"r":0,"i":6},{"b":354.5,"r":0,"i":0},{"b":354.5,"r":0,"i":28},{"b":355,"r":0,"i":5},{"b":355,"r":0,"i":3},{"b":355.5,"r":0,"i":6},{"b":356,"r":0,"i":11},{"b":356,"r":0,"i":7},{"b":358,"r":0,"i":21},{"b":358,"r":0,"i":17},{"b":359,"r":0,"i":0},{"b":359,"r":0,"i":3},{"b":360,"r":0,"i":5},{"b":360,"r":0,"i":6},{"b":360.5,"r":0,"i":3},{"b":361,"r":0,"i":4},{"b":361,"r":0,"i":17},{"b":361.5,"r":0,"i":21},{"b":361.75,"r":0,"i":12},{"b":362,"r":0,"i":0},{"b":362.25,"r":0,"i":6},{"b":362.5,"r":0,"i":2},{"b":363,"r":0,"i":0},{"b":363,"r":0,"i":7},{"b":363.5,"r":0,"i":14},{"b":363.75,"r":0,"i":26},{"b":364,"r":0,"i":61},{"b":364,"r":0,"i":62},{"b":364.5,"r":0,"i":10},{"b":365,"r":0,"i":11},{"b":365,"r":0,"i":29},{"b":365.5,"r":0,"i":63},{"b":365.75,"r":0,"i":1},{"b":366,"r":0,"i":15},{"b":366.25,"r":0,"i":3},{"b":366.5,"r":0,"i":64},{"b":367,"r":0,"i":11},{"b":367,"r":0,"i":6},{"b":367.5,"r":0,"i":7},{"b":367.75,"r":0,"i":14},{"b":368,"r":0,"i":26},{"b":368,"r":0,"i":9},{"b":368.5,"r":0,"i":20},{"b":369,"r":0,"i":4},{"b":369,"r":0,"i":17},{"b":369.5,"r":0,"i":31},{"b":369.75,"r":0,"i":12},{"b":370,"r":0,"i":0},{"b":370.25,"r":0,"i":6},{"b":370.5,"r":0,"i":2},{"b":371,"r":0,"i":0},{"b":371,"r":0,"i":3},{"b":371.5,"r":0,"i":10},{"b":371.75,"r":0,"i":9},{"b":372,"r":0,"i":52},{"b":372,"r":0,"i":15},{"b":372.5,"r":0,"i":64},{"b":373,"r":0,"i":65},{"b":373,"r":0,"i":22},{"b":373.5,"r":0,"i":6},{"b":373.75,"r":0,"i":5},{"b":374,"r":0,"i":33},{"b":374.25,"r":0,"i":28},{"b":374.5,"r":0,"i":1},{"b":374.75,"r":0,"i":10},{"b":375,"r":0,"i":24},{"b":375.25,"r":0,"i":4},{"b":375.5,"r":0,"i":6},{"b":375.75,"r":0,"i":31},{"b":376,"r":0,"i":8},{"b":376.75,"r":0,"i":4},{"b":377.5,"r":0,"i":31},{"b":378.25,"r":0,"i":6},{"b":379,"r":0,"i":7},{"b":379.75,"r":0,"i":6},{"b":379.75,"r":0,"i":62},{"b":380.5,"r":0,"i":64},{"b":380.5,"r":0,"i":47},{"b":381.5,"r":0,"i":4},{"b":381.75,"r":0,"i":6},{"b":382,"r":0,"i":31},{"b":382.75,"r":0,"i":0},{"b":383.5,"r":0,"i":5},{"b":384,"r":0,"i":33},{"b":384.75,"r":0,"i":4},{"b":385.5,"r":0,"i":9},{"b":386,"r":0,"i":16},{"b":387,"r":0,"i":66},{"b":387.75,"r":0,"i":67},{"b":388.5,"r":0,"i":68},{"b":389.5,"r":0,"i":69},{"b":389.75,"r":0,"i":70},{"b":390,"r":0,"i":60},{"b":390.75,"r":0,"i":8},{"b":391.5,"r":0,"i":54},{"b":392,"r":0,"i":11},{"b":392,"r":0,"i":8},{"b":393,"r":0,"i":10},{"b":393,"r":0,"i":1},{"b":395.5,"r":0,"i":62},{"b":395.5,"r":0,"i":47},{"b":396.5,"r":0,"i":6},{"b":396.5,"r":0,"i":64},{"b":397.5,"r":0,"i":62},{"b":397.5,"r":0,"i":47},{"b":399,"r":0,"i":17},{"b":399.5,"r":0,"i":21},{"b":400.5,"r":0,"i":0},{"b":400.5,"r":0,"i":3},{"b":403.5,"r":0,"i":6},{"b":404,"r":0,"i":5},{"b":405,"r":0,"i":8},{"b":406.5,"r":0,"i":1},{"b":406.5,"r":0,"i":15},{"b":408,"r":0,"i":31},{"b":408,"r":0,"i":3},{"b":408.5,"r":0,"i":0},{"b":409,"r":0,"i":5},{"b":409,"r":0,"i":6},{"b":409.5,"r":0,"i":7},{"b":409.75,"r":0,"i":18},{"b":410,"r":0,"i":26},{"b":410.25,"r":0,"i":14},{"b":410.5,"r":0,"i":20},{"b":411,"r":0,"i":4},{"b":411,"r":0,"i":17},{"b":411.5,"r":0,"i":31},{"b":412,"r":0,"i":0},{"b":412,"r":0,"i":3},{"b":412.5,"r":0,"i":5},{"b":413,"r":0,"i":11},{"b":413,"r":0,"i":6},{"b":413.5,"r":0,"i":7},{"b":413.75,"r":0,"i":14},{"b":414,"r":0,"i":26},{"b":414.25,"r":0,"i":4},{"b":414.5,"r":0,"i":24},{"b":414.75,"r":0,"i":21},{"b":415.5,"r":0,"i":32},{"b":416,"r":0,"i":31},{"b":416,"r":0,"i":17},{"b":416.5,"r":0,"i":3},{"b":417,"r":0,"i":0},{"b":417,"r":0,"i":1},{"b":417.5,"r":0,"i":12},{"b":417.75,"r":0,"i":2},{"b":418,"r":0,"i":6},{"b":418.25,"r":0,"i":4},{"b":418.5,"r":0,"i":8},{"b":419,"r":0,"i":14},{"b":419,"r":0,"i":26},{"b":419.5,"r":0,"i":4},{"b":420,"r":0,"i":10},{"b":420,"r":0,"i":20},{"b":420.5,"r":0,"i":1},{"b":421,"r":0,"i":28},{"b":421,"r":0,"i":3},{"b":421.5,"r":0,"i":6},{"b":421.75,"r":0,"i":2},{"b":422,"r":0,"i":7},{"b":422.25,"r":0,"i":18},{"b":422.5,"r":0,"i":26},{"b":422.75,"r":0,"i":10},{"b":423.5,"r":0,"i":4},{"b":423.75,"r":0,"i":24},{"b":424,"r":0,"i":31},{"b":424,"r":0,"i":21},{"b":424.5,"r":0,"i":0},{"b":425,"r":0,"i":5},{"b":425,"r":0,"i":6},{"b":425.5,"r":0,"i":8},{"b":426,"r":0,"i":60},{"b":426.5,"r":0,"i":8},{"b":427,"r":0,"i":11},{"b":427,"r":0,"i":54},{"b":427.5,"r":0,"i":8},{"b":428,"r":0,"i":10},{"b":428,"r":0,"i":26},{"b":428.5,"r":0,"i":4},{"b":429,"r":0,"i":21},{"b":429,"r":0,"i":24},{"b":429.5,"r":0,"i":1},{"b":429.75,"r":0,"i":0},{"b":430,"r":0,"i":3},{"b":430.25,"r":0,"i":2},{"b":430.5,"r":0,"i":6},{"b":431,"r":0,"i":11},{"b":431,"r":0,"i":7},{"b":431.5,"r":0,"i":26},{"b":432,"r":0,"i":10},{"b":432,"r":0,"i":20},{"b":432.5,"r":0,"i":4},{"b":433,"r":0,"i":31},{"b":433,"r":0,"i":54},{"b":433.5,"r":0,"i":7},{"b":433.75,"r":0,"i":32},{"b":434,"r":0,"i":26},{"b":434.25,"r":0,"i":21},{"b":434.5,"r":0,"i":20},{"b":435,"r":0,"i":26},{"b":435,"r":0,"i":9},{"b":435.5,"r":0,"i":3},{"b":436,"r":0,"i":11},{"b":436,"r":0,"i":6},{"b":436.5,"r":0,"i":33},{"b":437,"r":0,"i":13},{"b":437,"r":0,"i":63},{"b":437.5,"r":0,"i":33},{"b":437.75,"r":0,"i":11},{"b":438,"r":0,"i":1},{"b":438.25,"r":0,"i":10},{"b":438.5,"r":0,"i":24},{"b":438.75,"r":0,"i":4},{"b":439,"r":0,"i":26},{"b":439.25,"r":0,"i":21},{"b":439.5,"r":0,"i":3},{"b":439.75,"r":0,"i":0},{"b":440,"r":0,"i":13},{"b":440,"r":0,"i":50},{"b":440.5,"r":0,"i":35},{"b":441,"r":0,"i":10},{"b":441,"r":0,"i":9},{"b":441.5,"r":0,"i":4},{"b":442,"r":0,"i":21},{"b":442.25,"r":0,"i":12},{"b":442.5,"r":0,"i":0},{"b":442.75,"r":0,"i":6},{"b":443,"r":0,"i":2},{"b":443,"r":0,"i":5},{"b":443.5,"r":0,"i":18},{"b":444,"r":0,"i":10},{"b":444,"r":0,"i":8},{"b":445,"r":0,"i":4},{"b":445.25,"r":0,"i":17},{"b":445.5,"r":0,"i":21},{"b":445.75,"r":0,"i":12},{"b":446,"r":0,"i":0},{"b":446.75,"r":0,"i":5},{"b":447.5,"r":0,"i":11},{"b":448,"r":0,"i":70},{"b":448,"r":0,"i":54},{"b":448.5,"r":0,"i":8},{"b":449,"r":0,"i":18},{"b":449,"r":0,"i":26},{"b":449.5,"r":0,"i":10},{"b":450,"r":0,"i":4},{"b":450.25,"r":0,"i":24},{"b":450.5,"r":0,"i":16},{"b":450.75,"r":0,"i":6},{"b":451,"r":0,"i":0},{"b":451,"r":0,"i":28},{"b":451.5,"r":0,"i":3},{"b":452,"r":0,"i":10},{"b":453,"r":0,"i":4},{"b":453.25,"r":0,"i":17},{"b":453.5,"r":0,"i":21},{"b":453.75,"r":0,"i":12},{"b":454,"r":0,"i":0},{"b":454,"r":0,"i":28},{"b":454.5,"r":0,"i":5},{"b":455,"r":0,"i":11},{"b":455,"r":0,"i":6},{"b":455.5,"r":0,"i":7},{"b":456,"r":0,"i":14},{"b":456,"r":0,"i":26},{"b":456.5,"r":0,"i":20},{"b":457,"r":0,"i":4},{"b":457,"r":0,"i":17},{"b":459.5,"r":0,"i":31},{"b":459.5,"r":0,"i":3},{"b":460.5,"r":0,"i":11},{"b":460.5,"r":0,"i":6},{"b":461,"r":0,"i":7},{"b":461,"r":0,"i":8},{"b":461.5,"r":0,"i":10},{"b":461.5,"r":0,"i":26},{"b":462,"r":0,"i":4},{"b":462,"r":0,"i":20},{"b":462.5,"r":0,"i":21},{"b":463,"r":0,"i":4},{"b":463,"r":0,"i":17},{"b":463.5,"r":0,"i":31},{"b":464,"r":0,"i":0},{"b":464,"r":0,"i":12},{"b":464.5,"r":0,"i":6},{"b":465,"r":0,"i":2},{"b":465,"r":0,"i":7},{"b":467,"r":0,"i":4},{"b":467,"r":0,"i":17},{"b":467.5,"r":0,"i":21},{"b":468,"r":0,"i":0},{"b":468,"r":0,"i":12},{"b":468.5,"r":0,"i":6},{"b":469,"r":0,"i":2},{"b":469,"r":0,"i":7},{"b":470,"r":0,"i":18},{"b":470.25,"r":0,"i":26},{"b":470.5,"r":0,"i":10},{"b":470.75,"r":0,"i":24},{"b":471,"r":0,"i":4},{"b":471.25,"r":0,"i":6},{"b":471.5,"r":0,"i":31},{"b":471.75,"r":0,"i":7},{"b":472,"r":0,"i":18},{"b":474,"r":0,"i":27},{"b":474.25,"r":0,"i":9},{"b":474.5,"r":0,"i":25},{"b":474.75,"r":0,"i":24},{"b":475,"r":0,"i":10},{"b":475.5,"r":0,"i":6},{"b":477,"r":0,"i":33},{"b":477.25,"r":0,"i":4},{"b":477.5,"r":0,"i":26},{"b":477.75,"r":0,"i":21},{"b":478,"r":0,"i":24},{"b":478.75,"r":0,"i":1},{"b":479.5,"r":0,"i":3},{"b":480,"r":0,"i":11},{"b":480,"r":0,"i":6},{"b":482,"r":0,"i":24},{"b":482.25,"r":0,"i":14},{"b":482.5,"r":0,"i":26},{"b":482.75,"r":0,"i":4},{"b":483.5,"r":0,"i":3},{"b":484,"r":0,"i":6},{"b":484.25,"r":0,"i":31},{"b":484.5,"r":0,"i":7},{"b":484.75,"r":0,"i":18},{"b":485,"r":0,"i":26},{"b":485.25,"r":0,"i":19},{"b":485.5,"r":0,"i":24},{"b":485.75,"r":0,"i":4},{"b":486,"r":0,"i":26},{"b":486.75,"r":0,"i":3},{"b":487.25,"r":0,"i":6},{"b":487.5,"r":0,"i":31},{"b":488,"r":0,"i":32},{"b":488,"r":0,"i":8},{"b":489.5,"r":0,"i":17},{"b":490,"r":0,"i":16},{"b":490.25,"r":0,"i":46},{"b":490.5,"r":0,"i":4},{"b":490.75,"r":0,"i":17},{"b":491,"r":0,"i":21},{"b":491.5,"r":0,"i":0},{"b":491.5,"r":0,"i":12},{"b":493,"r":0,"i":6},{"b":493.25,"r":0,"i":2},{"b":493.5,"r":0,"i":7},{"b":493.75,"r":0,"i":18},{"b":494,"r":0,"i":26},{"b":494.75,"r":0,"i":20},{"b":495.25,"r":0,"i":10},{"b":495.5,"r":0,"i":9},{"b":496,"r":0,"i":4},{"b":496,"r":0,"i":20},{"b":497.5,"r":0,"i":17},{"b":498,"r":0,"i":21},{"b":498.25,"r":0,"i":3},{"b":498.5,"r":0,"i":0},{"b":498.75,"r":0,"i":6},{"b":499.5,"r":0,"i":10},{"b":501.5,"r":0,"i":4},{"b":502,"r":0,"i":24},{"b":503,"r":0,"i":10}],"colorNotesData":[{"x":0,"y":0,"c":0,"d":1,"a":0},{"x":2,"y":0,"c":1,"d":1,"a":0},{"x":0,"y":1,"c":0,"d":0,"a":0},{"x":2,"y":2,"c":1,"d":0,"a":0},{"x":2,"y":0,"c":0,"d":7,"a":0},{"x":0,"y":2,"c":0,"d":0,"a":0},{"x":1,"y":0,"c":1,"d":6,"a":0},{"x":2,"y":0,"c":1,"d":5,"a":0},{"x":3,"y":1,"c":1,"d":5,"a":0},{"x":3,"y":1,"c":1,"d":1,"a":0},{"x":1,"y":2,"c":0,"d":0,"a":0},{"x":0,"y":1,"c":0,"d":6,"a":0},{"x":2,"y":0,"c":1,"d":0,"a":0},{"x":0,"y":1,"c":1,"d":6,"a":0},{"x":1,"y":0,"c":0,"d":0,"a":0},{"x":3,"y":1,"c":0,"d":7,"a":0},{"x":2,"y":0,"c":0,"d":4,"a":0},{"x":3,"y":1,"c":1,"d":7,"a":0},{"x":1,"y":0,"c":0,"d":1,"a":0},{"x":1,"y":1,"c":0,"d":0,"a":0},{"x":3,"y":2,"c":1,"d":0,"a":0},{"x":1,"y":0,"c":0,"d":4,"a":0},{"x":2,"y":1,"c":1,"d":0,"a":0},{"x":2,"y":0,"c":0,"d":0,"a":0},{"x":3,"y":1,"c":1,"d":0,"a":0},{"x":2,"y":0,"c":0,"d":1,"a":0},{"x":3,"y":0,"c":1,"d":1,"a":0},{"x":2,"y":2,"c":0,"d":0,"a":0},{"x":0,"y":1,"c":0,"d":1,"a":0},{"x":1,"y":0,"c":1,"d":0,"a":0},{"x":0,"y":0,"c":1,"d":6,"a":0},{"x":0,"y":1,"c":0,"d":4,"a":0},{"x":1,"y":0,"c":0,"d":7,"a":0},{"x":1,"y":0,"c":1,"d":5,"a":0},{"x":0,"y":2,"c":0,"d":4,"a":0},{"x":2,"y":2,"c":1,"d":5,"a":0},{"x":3,"y":0,"c":1,"d":7,"a":0},{"x":1,"y":1,"c":0,"d":4,"a":0},{"x":3,"y":0,"c":0,"d":3,"a":0},{"x":2,"y":0,"c":0,"d":2,"a":0},{"x":2,"y":2,"c":1,"d":4,"a":0},{"x":2,"y":0,"c":0,"d":3,"a":0},{"x":0,"y":0,"c":0,"d":4,"a":0},{"x":1,"y":2,"c":1,"d":7,"a":0},{"x":1,"y":2,"c":1,"d":0,"a":0},{"x":1,"y":2,"c":1,"d":5,"a":0},{"x":3,"y":1,"c":1,"d":4,"a":0},{"x":3,"y":2,"c":1,"d":5,"a":0},{"x":1,"y":2,"c":0,"d":6,"a":0},{"x":1,"y":1,"c":1,"d":6,"a":0},{"x":1,"y":2,"c":1,"d":6,"a":0},{"x":2,"y":2,"c":1,"d":7,"a":0},{"x":2,"y":2,"c":0,"d":7,"a":0},{"x":1,"y":0,"c":0,"d":3,"a":0},{"x":2,"y":0,"c":1,"d":6,"a":0},{"x":2,"y":0,"c":1,"d":4,"a":0},{"x":2,"y":2,"c":0,"d":5,"a":0},{"x":3,"y":0,"c":1,"d":5,"a":0},{"x":0,"y":0,"c":0,"d":2,"a":0},{"x":1,"y":0,"c":0,"d":2,"a":0},{"x":1,"y":0,"c":1,"d":2,"a":0},{"x":2,"y":1,"c":0,"d":7,"a":0},{"x":3,"y":0,"c":0,"d":7,"a":0},{"x":1,"y":0,"c":0,"d":5,"a":0},{"x":1,"y":2,"c":0,"d":4,"a":0},{"x":0,"y":2,"c":0,"d":6,"a":0},{"x":0,"y":0,"c":0,"d":6,"a":0},{"x":2,"y":1,"c":1,"d":5,"a":0},{"x":0,"y":0,"c":1,"d":2,"a":0},{"x":1,"y":0,"c":1,"d":3,"a":0},{"x":1,"y":2,"c":0,"d":5,"a":0},{"x":2,"y":0,"c":0,"d":5,"a":0},{"x":3,"y":0,"c":0,"d":1,"a":0},{"x":1,"y":2,"c":0,"d":1,"a":0},{"x":3,"y":0,"c":0,"d":0,"a":0},{"x":3,"y":1,"c":0,"d":0,"a":0},{"x":1,"y":0,"c":0,"d":6,"a":0},{"x":3,"y":2,"c":0,"d":0,"a":0},{"x":3,"y":2,"c":0,"d":5,"a":0},{"x":0,"y":0,"c":0,"d":0,"a":0},{"x":2,"y":2,"c":0,"d":1,"a":0}],"bombNotes":[{"b":145,"r":0,"i":0},{"b":145,"r":0,"i":1}],"bombNotesData":[{"x":1,"y":0},{"x":2,"y":0}],"arcs":[{"hb":4,"tb":8,"hr":0,"tr":0,"hi":2,"ti":0,"ai":0},{"hb":4,"tb":8,"hr":0,"tr":0,"hi":22,"ti":25,"ai":0},{"hb":27,"tb":28,"hr":0,"tr":0,"hi":5,"ti":11,"ai":0},{"hb":68,"tb":70,"hr":0,"tr":0,"hi":5,"ti":11,"ai":0},{"hb":68,"tb":70,"hr":0,"tr":0,"hi":6,"ti":71,"ai":0},{"hb":70,"tb":72,"hr":0,"tr":0,"hi":7,"ti":72,"ai":0},{"hb":89,"tb":91.5,"hr":0,"tr":0,"hi":18,"ti":34,"ai":0},{"hb":89,"tb":91.5,"hr":0,"tr":0,"hi":3,"ti":66,"ai":0},{"hb":93.5,"tb":95.5,"hr":0,"tr":0,"hi":30,"ti":71,"ai":0},{"hb":93.5,"tb":95,"hr":0,"tr":0,"hi":34,"ti":11,"ai":0},{"hb":95.5,"tb":96.5,"hr":0,"tr":0,"hi":7,"ti":72,"ai":0},{"hb":96.5,"tb":98.5,"hr":0,"tr":0,"hi":10,"ti":73,"ai":1},{"hb":96.5,"tb":98.5,"hr":0,"tr":0,"hi":26,"ti":74,"ai":1},{"hb":101,"tb":102.5,"hr":0,"tr":0,"hi":31,"ti":18,"ai":0},{"hb":102.5,"tb":104,"hr":0,"tr":0,"hi":13,"ti":75,"ai":0},{"hb":121,"tb":124.5,"hr":0,"tr":0,"hi":10,"ti":4,"ai":0},{"hb":121,"tb":123.5,"hr":0,"tr":0,"hi":8,"ti":15,"ai":0},{"hb":124.5,"tb":125.5,"hr":0,"tr":0,"hi":4,"ti":31,"ai":0},{"hb":125.5,"tb":127,"hr":0,"tr":0,"hi":3,"ti":76,"ai":0},{"hb":127.5,"tb":128.5,"hr":0,"tr":0,"hi":28,"ti":5,"ai":0},{"hb":133,"tb":134.5,"hr":0,"tr":0,"hi":3,"ti":15,"ai":0},{"hb":196,"tb":198,"hr":0,"tr":0,"hi":17,"ti":27,"ai":0},{"hb":217,"tb":219,"hr":0,"tr":0,"hi":20,"ti":15,"ai":0},{"hb":249,"tb":252.5,"hr":0,"tr":0,"hi":10,"ti":4,"ai":0},{"hb":249,"tb":251.5,"hr":0,"tr":0,"hi":8,"ti":15,"ai":0},{"hb":252.5,"tb":253.5,"hr":0,"tr":0,"hi":4,"ti":31,"ai":0},{"hb":253.5,"tb":255,"hr":0,"tr":0,"hi":3,"ti":76,"ai":0},{"hb":255.5,"tb":256.5,"hr":0,"tr":0,"hi":28,"ti":5,"ai":0},{"hb":261,"tb":262.75,"hr":0,"tr":0,"hi":9,"ti":23,"ai":0},{"hb":280,"tb":281.75,"hr":0,"tr":0,"hi":20,"ti":15,"ai":0},{"hb":284,"tb":285.75,"hr":0,"tr":0,"hi":5,"ti":11,"ai":0},{"hb":298,"tb":300,"hr":0,"tr":0,"hi":26,"ti":27,"ai":0},{"hb":300,"tb":301.5,"hr":0,"tr":0,"hi":3,"ti":11,"ai":0},{"hb":306,"tb":308,"hr":0,"tr":0,"hi":11,"ti":21,"ai":0},{"hb":306,"tb":308,"hr":0,"tr":0,"hi":33,"ti":15,"ai":0},{"hb":314,"tb":316,"hr":0,"tr":0,"hi":6,"ti":77,"ai":0},{"hb":316,"tb":317.5,"hr":0,"tr":0,"hi":10,"ti":4,"ai":0},{"hb":322,"tb":324,"hr":0,"tr":0,"hi":55,"ti":25,"ai":0},{"hb":322,"tb":324,"hr":0,"tr":0,"hi":15,"ti":10,"ai":0},{"hb":324,"tb":325.5,"hr":0,"tr":0,"hi":10,"ti":11,"ai":0},{"hb":356,"tb":358,"hr":0,"tr":0,"hi":11,"ti":21,"ai":0},{"hb":356,"tb":358,"hr":0,"tr":0,"hi":7,"ti":15,"ai":0},{"hb":393,"tb":395.5,"hr":0,"tr":0,"hi":10,"ti":62,"ai":0},{"hb":393,"tb":395.5,"hr":0,"tr":0,"hi":1,"ti":78,"ai":0},{"hb":397.5,"tb":399.5,"hr":0,"tr":0,"hi":62,"ti":21,"ai":0},{"hb":397.5,"tb":399,"hr":0,"tr":0,"hi":47,"ti":15,"ai":0},{"hb":399.5,"tb":400.5,"hr":0,"tr":0,"hi":21,"ti":0,"ai":0},{"hb":400.5,"tb":402.5,"hr":0,"tr":0,"hi":0,"ti":79,"ai":1},{"hb":400.5,"tb":402.5,"hr":0,"tr":0,"hi":3,"ti":80,"ai":1},{"hb":405,"tb":406.5,"hr":0,"tr":0,"hi":8,"ti":25,"ai":0},{"hb":406.5,"tb":408,"hr":0,"tr":0,"hi":1,"ti":27,"ai":0},{"hb":406.5,"tb":408,"hr":0,"tr":0,"hi":15,"ti":31,"ai":0},{"hb":425,"tb":427,"hr":0,"tr":0,"hi":5,"ti":11,"ai":0},{"hb":457,"tb":459.5,"hr":0,"tr":0,"hi":4,"ti":31,"ai":0},{"hb":457,"tb":459.5,"hr":0,"tr":0,"hi":17,"ti":27,"ai":0},{"hb":472,"tb":474,"hr":0,"tr":0,"hi":18,"ti":27,"ai":0},{"hb":480,"tb":482.25,"hr":0,"tr":0,"hi":11,"ti":14,"ai":0},{"hb":480,"tb":482,"hr":0,"tr":0,"hi":6,"ti":75,"ai":0},{"hb":488,"tb":490,"hr":0,"tr":0,"hi":32,"ti":16,"ai":0},{"hb":488,"tb":489.5,"hr":0,"tr":0,"hi":8,"ti":15,"ai":0},{"hb":496,"tb":497.5,"hr":0,"tr":0,"hi":20,"ti":15,"ai":0}],"arcsData":[{"m":1,"tm":1,"a":0},{"m":1,"tm":0,"a":0}],"chains":[],"chainsData":[],"obstacles":[{"b":4,"r":0,"i":0},{"b":4,"r":0,"i":1},{"b":8,"r":0,"i":2},{"b":8.5,"r":0,"i":3},{"b":9,"r":0,"i":2},{"b":9.5,"r":0,"i":4},{"b":11,"r":0,"i":5},{"b":12,"r":0,"i":3},{"b":12.5,"r":0,"i":2},{"b":13,"r":0,"i":3},{"b":13.5,"r":0,"i":5},{"b":15,"r":0,"i":4},{"b":16,"r":0,"i":2},{"b":16.5,"r":0,"i":3},{"b":17,"r":0,"i":2},{"b":17.5,"r":0,"i":4},{"b":19,"r":0,"i":5},{"b":20,"r":0,"i":3},{"b":20.5,"r":0,"i":2},{"b":21,"r":0,"i":3},{"b":21.5,"r":0,"i":5},{"b":23,"r":0,"i":4},{"b":24,"r":0,"i":2},{"b":24.5,"r":0,"i":3},{"b":25,"r":0,"i":2},{"b":25.5,"r":0,"i":4},{"b":27,"r":0,"i":5},{"b":28,"r":0,"i":3},{"b":28.5,"r":0,"i":2},{"b":29,"r":0,"i":3},{"b":29.5,"r":0,"i":5},{"b":31,"r":0,"i":4},{"b":32,"r":0,"i":2},{"b":32.5,"r":0,"i":3},{"b":33,"r":0,"i":2},{"b":33.5,"r":0,"i":4},{"b":35,"r":0,"i":5},{"b":36,"r":0,"i":3},{"b":36.5,"r":0,"i":2},{"b":37,"r":0,"i":3},{"b":37.5,"r":0,"i":5},{"b":39,"r":0,"i":4},{"b":42,"r":0,"i":6},{"b":42,"r":0,"i":7},{"b":44,"r":0,"i":8},{"b":44.75,"r":0,"i":9},{"b":47.5,"r":0,"i":10},{"b":47.5,"r":0,"i":11},{"b":68,"r":0,"i":12},{"b":70.5,"r":0,"i":13},{"b":75.75,"r":0,"i":14},{"b":76.5,"r":0,"i":14},{"b":89,"r":0,"i":15},{"b":93.5,"r":0,"i":12},{"b":96.5,"r":0,"i":16},{"b":101,"r":0,"i":12},{"b":103,"r":0,"i":13},{"b":107.75,"r":0,"i":14},{"b":108.5,"r":0,"i":14},{"b":115.75,"r":0,"i":17},{"b":116.5,"r":0,"i":18},{"b":121,"r":0,"i":16},{"b":125.5,"r":0,"i":19},{"b":128.5,"r":0,"i":15},{"b":136.5,"r":0,"i":20},{"b":137.5,"r":0,"i":21},{"b":138.5,"r":0,"i":20},{"b":139.5,"r":0,"i":21},{"b":140.5,"r":0,"i":20},{"b":141.5,"r":0,"i":21},{"b":142.5,"r":0,"i":20},{"b":143.5,"r":0,"i":21},{"b":145,"r":0,"i":22},{"b":145,"r":0,"i":23},{"b":170,"r":0,"i":10},{"b":170,"r":0,"i":11},{"b":172,"r":0,"i":9},{"b":172.5,"r":0,"i":8},{"b":175.5,"r":0,"i":10},{"b":175.5,"r":0,"i":11},{"b":196,"r":0,"i":24},{"b":198,"r":0,"i":25},{"b":217,"r":0,"i":26},{"b":235.75,"r":0,"i":18},{"b":236.5,"r":0,"i":18},{"b":243.75,"r":0,"i":17},{"b":244.5,"r":0,"i":18},{"b":249,"r":0,"i":16},{"b":253.5,"r":0,"i":19},{"b":256.5,"r":0,"i":15},{"b":264.5,"r":0,"i":20},{"b":265.5,"r":0,"i":21},{"b":266.5,"r":0,"i":20},{"b":267.5,"r":0,"i":21},{"b":268.5,"r":0,"i":20},{"b":269.5,"r":0,"i":21},{"b":270.5,"r":0,"i":20},{"b":271.5,"r":0,"i":21},{"b":272.5,"r":0,"i":20},{"b":273.5,"r":0,"i":21},{"b":274.5,"r":0,"i":20},{"b":275.5,"r":0,"i":21},{"b":276.5,"r":0,"i":20},{"b":277.5,"r":0,"i":21},{"b":278.5,"r":0,"i":20},{"b":279.5,"r":0,"i":21},{"b":280,"r":0,"i":27},{"b":284,"r":0,"i":28},{"b":288,"r":0,"i":29},{"b":288.5,"r":0,"i":21},{"b":289.5,"r":0,"i":20},{"b":290.5,"r":0,"i":21},{"b":291.5,"r":0,"i":20},{"b":292.5,"r":0,"i":21},{"b":293.5,"r":0,"i":20},{"b":294.5,"r":0,"i":21},{"b":298,"r":0,"i":30},{"b":300,"r":0,"i":12},{"b":304.5,"r":0,"i":19},{"b":306,"r":0,"i":12},{"b":308,"r":0,"i":13},{"b":312,"r":0,"i":13},{"b":314,"r":0,"i":12},{"b":316,"r":0,"i":13},{"b":320.5,"r":0,"i":4},{"b":322.25,"r":0,"i":31},{"b":324,"r":0,"i":13},{"b":328,"r":0,"i":2},{"b":328.5,"r":0,"i":3},{"b":329,"r":0,"i":2},{"b":329.5,"r":0,"i":4},{"b":331,"r":0,"i":5},{"b":332,"r":0,"i":3},{"b":332.5,"r":0,"i":2},{"b":333,"r":0,"i":3},{"b":333.5,"r":0,"i":5},{"b":335,"r":0,"i":4},{"b":356.25,"r":0,"i":32},{"b":358.25,"r":0,"i":33},{"b":379.75,"r":0,"i":18},{"b":380.5,"r":0,"i":18},{"b":393,"r":0,"i":16},{"b":397.5,"r":0,"i":30},{"b":400.5,"r":0,"i":15},{"b":405,"r":0,"i":30},{"b":425,"r":0,"i":34},{"b":457.25,"r":0,"i":35},{"b":472,"r":0,"i":36},{"b":475.5,"r":0,"i":12},{"b":480.25,"r":0,"i":37},{"b":488,"r":0,"i":30},{"b":491.5,"r":0,"i":19},{"b":495,"r":0,"i":13},{"b":499.5,"r":0,"i":30},{"b":503,"r":0,"i":19}],"obstaclesData":[{"x":-1,"y":0,"d":4,"w":1,"h":3},{"x":4,"y":0,"d":4,"w":1,"h":3},{"x":4,"y":2,"d":0.5,"w":1,"h":3},{"x":-1,"y":2,"d":0.5,"w":1,"h":3},{"x":-1,"y":2,"d":1,"w":1,"h":3},{"x":4,"y":2,"d":1,"w":1,"h":3},{"x":-1,"y":0,"d":0.75,"w":1,"h":5},{"x":4,"y":0,"d":0.75,"w":1,"h":5},{"x":-1,"y":2,"d":0.036,"w":1,"h":3},{"x":4,"y":2,"d":0.036,"w":1,"h":3},{"x":-1,"y":0,"d":0.5,"w":1,"h":5},{"x":4,"y":0,"d":0.5,"w":1,"h":5},{"x":3,"y":2,"d":1.5,"w":1,"h":3},{"x":0,"y":2,"d":1,"w":1,"h":3},{"x":3,"y":2,"d":0.5,"w":1,"h":3},{"x":3,"y":2,"d":2.5,"w":1,"h":3},{"x":0,"y":2,"d":2.5,"w":1,"h":3},{"x":3,"y":2,"d":0.25,"w":1,"h":3},{"x":0,"y":2,"d":0.5,"w":1,"h":3},{"x":3,"y":2,"d":1,"w":1,"h":3},{"x":5,"y":0,"d":0.5,"w":1,"h":2},{"x":-2,"y":0,"d":0.5,"w":1,"h":2},{"x":0,"y":0,"d":0.75,"w":1,"h":5},{"x":3,"y":0,"d":0.75,"w":1,"h":5},{"x":-1,"y":2,"d":2,"w":1,"h":3},{"x":4,"y":2,"d":2,"w":1,"h":3},{"x":4,"y":2,"d":2.5,"w":1,"h":3},{"x":4,"y":2,"d":4,"w":1,"h":3},{"x":-1,"y":2,"d":4,"w":1,"h":3},{"x":4,"y":2,"d":1.5,"w":1,"h":3},{"x":0,"y":2,"d":1.5,"w":1,"h":3},{"x":3,"y":2,"d":1.25,"w":1,"h":3},{"x":0,"y":2,"d":1.25,"w":1,"h":3},{"x":3,"y":2,"d":0.75,"w":1,"h":3},{"x":-1,"y":2,"d":2.5,"w":1,"h":3},{"x":3,"y":2,"d":2.25,"w":1,"h":3},{"x":0,"y":2,"d":2,"w":1,"h":3},{"x":0,"y":2,"d":1.75,"w":1,"h":3}],"njsEvents":[{"b":0,"i":0},{"b":133,"i":0},{"b":134,"i":1},{"b":144.75,"i":2},{"b":145.25,"i":3},{"b":145.5,"i":1},{"b":296,"i":4},{"b":297,"i":5},{"b":344,"i":0},{"b":344.5,"i":6},{"b":376,"i":4},{"b":377,"i":5},{"b":407,"i":0},{"b":407.75,"i":1},{"b":472,"i":4},{"b":473,"i":5}],"njsEventData":[{"p":0,"e":-1,"d":-2},{"p":0,"e":1,"d":0},{"p":1,"e":-1,"d":0},{"p":0,"e":0,"d":10},{"p":0,"e":-1,"d":0},{"p":0,"e":2,"d":-2},{"p":0,"e":2,"d":0}]}